aristaflow/__init__.py
aristaflow/absence_service.py
aristaflow/abstract_service.py
aristaflow/activity_context.py
aristaflow/activity_service.py
aristaflow/client_platform.py
aristaflow/client_service.py
aristaflow/configuration.py
aristaflow/delegation_service.py
aristaflow/execution_history_service.py
aristaflow/html_gui_context.py
aristaflow/image_renderer_service.py
aristaflow/org_model_service.py
aristaflow/process_service.py
aristaflow/remote_html_service.py
aristaflow/remote_iterator_handler.py
aristaflow/rest_helper.py
aristaflow/service_provider.py
aristaflow/sse_helper.py
aristaflow/utils.py
aristaflow/worklist_model.py
aristaflow/worklist_service.py
aristaflowpy-1.15.6.dist-info/licenses/LICENSE
aristaflowpy-1.15.6.dist-info/METADATA
aristaflowpy-1.15.6.dist-info/WHEEL
aristaflowpy-1.15.6.dist-info/top_level.txt
aristaflowpy-1.15.6.dist-info/RECORD
