Metadata-Version: 2.4
Name: aristaflowpy
Version: 1.15.6
Summary: AristaFlow BPM
Home-page: https://github.com/aristaflow/aristaflowpy
Author-email: info@aristaflow.com
Keywords: AristaFlow,BPM,Workflow,REST
License-File: LICENSE
Requires-Dist: urllib3>=1.15
Requires-Dist: six>=1.10
Requires-Dist: certifi
Requires-Dist: python-dateutil
Requires-Dist: sseclient
Dynamic: author-email
Dynamic: description
Dynamic: home-page
Dynamic: keywords
Dynamic: license-file
Dynamic: requires-dist
Dynamic: summary
